Metadata-Version: 2.1
Name: py-host
Version: 0.0.8
Summary: modify format of msg to log center of ys.
Home-page: https://github.com/wikensmith/py-host.git
Author: wiken
Author-email: wiken01@qq.com
License: UNKNOWN
Platform: UNKNOWN
Classifier: Programming Language :: Python :: 3
Requires-Dist: APScheduler (==3.6.3)
Requires-Dist: certifi (==2019.9.11)
Requires-Dist: chardet (==3.0.4)
Requires-Dist: idna (==2.8)
Requires-Dist: pika (==1.1.0)
Requires-Dist: pymongo (==3.9.0)
Requires-Dist: pymssql (==2.1.4)
Requires-Dist: PyMySQL (==0.9.3)
Requires-Dist: python-dateutil (==2.8.1)
Requires-Dist: python-redis-lock (==3.3.1)
Requires-Dist: pytz (==2019.3)
Requires-Dist: redis (==3.3.11)
Requires-Dist: redlock-py (==1.0.8)
Requires-Dist: requests (==2.22.0)
Requires-Dist: retrying (==1.3.3)
Requires-Dist: six (==1.13.0)
Requires-Dist: suds-py3 (==1.3.4.0)
Requires-Dist: tzlocal (==2.0.0)
Requires-Dist: urllib3 (==1.25.7)
